paapi5.py
paapi5-0.1.0.dist-info/WHEEL
paapi5-0.1.0.dist-info/METADATA
paapi5-0.1.0.dist-info/RECORD
