Metadata-Version: 2.4
Name: paapi5
Version: 0.1.0
Summary: Amazon Product Advertising API 5.0 Wrapper
Requires-Python: >=3.12
Requires-Dist: python-amazon-paapi>=5.0.1
